LICENSE.txt
MANIFEST.in
README.rst
setup.cfg
setup.py
./__init__.py
./setup.py
./mangenerator/__init__.py
./mangenerator/mangenerator.py
locale/es.po
mangenerator/__init__.py
mangenerator/mangenerator.py
mangenerator.egg-info/PKG-INFO
mangenerator.egg-info/SOURCES.txt
mangenerator.egg-info/dependency_links.txt
mangenerator.egg-info/entry_points.txt
mangenerator.egg-info/not-zip-safe
mangenerator.egg-info/top_level.txt
mangenerator/locale/es/LC_MESSAGES/mangenerator.mo