Metadata-Version: 2.1
Name: mangenerator
Version: 0.4.0
Summary: Python module to generate man documentation
Home-page: https://mangenerator.sourceforge.io/
Author: Turulomio
Author-email: turulomio@yahoo.es
License: GPL-3
Keywords: man generator
Platform: UNKNOWN
Classifier: Development Status :: 4 - Beta
Classifier: Intended Audience :: Developers
Classifier: Topic :: Software Development :: Build Tools
Classifier: License :: OSI Approved :: GNU General Public License v3 (GPLv3)
Classifier: Programming Language :: Python :: 3
